{
  "articles": [
    {
      "id": 1,
      "title": "Thị trường vàng tại Việt Nam có nhiều chuyển biến mới",
      "summary": "<a href=\"https://dantri.com.vn/kinh-doanh/thi-truong-vang-tai-viet-nam-co-nhieu-chuyen-bien-moi-20251212133618487.htm\"><img src=\"https://icdn.dantri.com.vn/2025/10/10/giam-thue-xuat-khau-xuong-0-voi-vang-trang-suc-my-nghe-1760100387645.jpg\" /></a>(Dân trí) - Từ việc xoá bỏ cơ chế độc quyền, chính thức đánh thuế mua bán vàng miếng... mới đây Quốc hội vừa có yêu cầu sớm lập sàn giao dịch vàng."
    },
    {
      "id": 2,
      "title": "Ngày 22/12, báo Dân trí tổ chức Diễn đàn ESG Việt Nam 2025",
      "summary": "<a href=\"https://dantri.com.vn/kinh-doanh/ngay-2212-bao-dan-tri-to-chuc-dien-dan-esg-viet-nam-2025-20251211205252277.htm\"><img src=\"https://icdn.dantri.com.vn/2025/12/11/thumbpng-1765460976234.png\" /></a>(Dân trí) - Diễn đàn ESG Việt Nam 2025 được báo Dân trí tổ chức ngày 22/12 tại Hà Nội, là nơi quy tụ lãnh đạo, chuyên gia và doanh nghiệp trao đổi nhiều nội dung hấp dẫn."
    },
    {
      "id": 3,
      "title": "Ngân hàng Nhà nước phát hiện gần 600.000 tài khoản thanh toán đáng ngờ",
      "summary": "<a href=\"https://dantri.com.vn/kinh-doanh/ngan-hang-nha-nuoc-phat-hien-gan-600000-tai-khoan-thanh-toan-dang-ngo-20251212135730611.htm\"><img src=\"https://icdn.dantri.com.vn/2023/04/20/vpbank-giao-dich29-edited-1681965295546.jpeg\" /></a>(Dân trí) - 592.000 tài khoản/ví điện tử bị xác định có dấu hiệu gian lận từ đầu năm. 2,13 triệu lượt khách hàng được cảnh báo, hơn 670.000 lượt khách hàng đã tạm dừng/hủy bỏ giao dịch sau khi nhận được cảnh báo."
    }
  ]
}