{
  "articles": [
    {
      "id": 1,
      "title": "Cổ phiếu Vietjet có diễn biến lạ, Vinpearl đón tin vui",
      "summary": "<a href=\"https://dantri.com.vn/kinh-doanh/co-phieu-vietjet-co-dien-bien-la-vinpearl-don-tin-vui-20251127151948487.htm\"><img src=\"https://icdn.dantri.com.vn/2024/04/22/chungkhoan4-crop-1713756859344.jpeg\" /></a>(Dân trí) - Cổ phiếu Vietjet giảm phiên thứ 2 liên tiếp, còn Vinpearl được đưa ra khỏi danh sách chứng khoán không đủ điều kiện giao dịch ký quỹ."
    },
    {
      "id": 2,
      "title": "HDBank muốn bán vốn tại Vietjet",
      "summary": "<a href=\"https://dantri.com.vn/kinh-doanh/hdbank-muon-ban-von-tai-vietjet-20251127150427101.htm\"><img src=\"https://icdn.dantri.com.vn/2021/06/29/vjchvnhangkhongnoibai-crop-1624949932350.jpeg\" /></a>(Dân trí) - Động thái bán vốn diễn ra sau khi cổ phiếu VJC có những phiên tăng giá liên tục. Thị giá VJC đang vào mức 200.000 đồng/cổ phiếu, tăng gấp đôi kể từ đầu năm."
    },
    {
      "id": 3,
      "title": "Giá xăng dầu giảm, có loại giảm đến hơn 1.000 đồng/lít",
      "summary": "<a href=\"https://dantri.com.vn/kinh-doanh/gia-xang-dau-giam-co-loai-giam-den-hon-1000-donglit-20251127142303635.htm\"><img src=\"https://icdn.dantri.com.vn/2025/01/22/gia-xangmquan-edited-1737484482269.jpeg\" /></a>(Dân trí) - Trong kỳ điều chỉnh ngày 27/11, giá xăng dầu cùng giảm, trong đó giá dầu diesel giảm mạnh 1.020 đồng/lít."
    }
  ]
}