{
  "articles": [
    {
      "id": 1,
      "title": "Biểu thuế thu nhập cá nhân còn 5 bậc, nhiều người ra khỏi diện nộp thuế",
      "summary": "<a href=\"https://dantri.com.vn/kinh-doanh/bieu-thue-thu-nhap-ca-nhan-con-5-bac-nhieu-nguoi-ra-khoi-dien-nop-thue-20251210095533952.htm\"><img src=\"https://icdn.dantri.com.vn/2025/11/19/giao-dich-ngan-hangthanh-dong-45jpg-1763525781005.jpg?watermark=true\" /></a>(Dân trí) - Biểu thuế thu nhập cá nhân từ 7 xuống 5 bậc, mức thuế cao nhất vẫn giữ 35%, giúp giảm nghĩa vụ thuế cho người làm công và đưa nhiều cá nhân thu nhập trung bình - thấp ra khỏi diện phải nộp thuế."
    },
    {
      "id": 2,
      "title": "Dự báo đáng chú ý về giá xăng ngày mai",
      "summary": "<a href=\"https://dantri.com.vn/kinh-doanh/du-bao-dang-chu-y-ve-gia-xang-ngay-mai-20251210012557198.htm\"><img src=\"https://icdn.dantri.com.vn/2025/02/13/nguoi-dan-do-xang14-edited-1739430902457.jpeg\" /></a>(Dân trí) - Nhiều doanh nghiệp dự báo giá xăng dầu trong nước sẽ cùng giảm trong kỳ điều hành ngày 11/12, trong đó giá xăng có thể quay đầu giảm 200-400 đồng/lít."
    },
    {
      "id": 3,
      "title": "Tiệm vàng Thanh Hóa doanh thu 5.000 tỷ: Hé lộ quá trình tăng vốn \"thần tốc\"",
      "summary": "<a href=\"https://dantri.com.vn/kinh-doanh/tiem-vang-thanh-hoa-doanh-thu-5000-ty-he-lo-qua-trinh-tang-von-than-toc-20251210010553537.htm\"><img src=\"https://icdn.dantri.com.vn/2025/12/10/4925012576908105801550253995419531399626224n-cropped-1765303374705.jpg\" /></a>(Dân trí) - Trong hơn 3 năm, Công ty TNHH Thương mại Vàng bạc Kim Chung đã tăng vốn gấp 25 lần, từ 2 tỷ đồng lên 50 tỷ đồng. Công an xác định doanh thu giai đoạn 2020-2025 của doanh nghiệp đạt tới 5.000 tỷ đồng."
    }
  ]
}