{
  "articles": [
    {
      "id": 1,
      "title": "Đồng USD suy yếu, Ngân hàng Nhà nước có thêm dư địa điều hành lãi suất",
      "summary": "<a href=\"https://dantri.com.vn/kinh-doanh/dong-usd-suy-yeu-ngan-hang-nha-nuoc-co-them-du-dia-dieu-hanh-lai-suat-20251216133316896.htm\"><img src=\"https://icdn.dantri.com.vn/2025/12/16/tien-22manh-quan-cropped-cropped-1765866522790.jpg\" /></a>(Dân trí) - USD tự do giảm sâu giúp giảm áp lực tỷ giá. Đây là cơ hội để Ngân hàng Nhà nước có thêm dư địa điều hành lãi suất trong bối cảnh thanh khoản hệ thống đang căng thẳng."
    },
    {
      "id": 2,
      "title": "Người đầu tiên trên thế giới sở hữu 600 tỷ USD",
      "summary": "<a href=\"https://dantri.com.vn/kinh-doanh/nguoi-dau-tien-tren-the-gioi-so-huu-600-ty-usd-20251216135204840.htm\"><img src=\"https://icdn.dantri.com.vn/2025/12/16/nguoi-dau-tien-tren-the-gioi-so-huu-600-ty-usd-cropped-1765867469085.jpg\" /></a>(Dân trí) - Tài sản của tỷ phú Elon Musk tăng thêm 168 tỷ USD chỉ trong một phiên, tạo cú bứt phá lịch sử, đưa tỷ phú này tiến gần hơn tới mục tiêu trở thành người sở hữu 1.000 tỷ USD đầu tiên trên thế giới."
    },
    {
      "id": 3,
      "title": "3 hãng hàng không Việt dùng máy bay gì khi \"xông đất\" sân bay Long Thành?",
      "summary": "<a href=\"https://dantri.com.vn/kinh-doanh/3-hang-hang-khong-viet-dung-may-bay-gi-khi-xong-dat-san-bay-long-thanh-20251216123309937.htm\"><img src=\"https://icdn.dantri.com.vn/2025/12/16/long-thanh-cropped-1765863114677.jpg\" /></a>(Dân trí) - Các chuyến \"xông đất\" này sẽ do 3 hãng hàng không Việt Nam gồm Vietnam Airlines, Vietjet Air và Bamboo Airways thực hiện."
    }
  ]
}