{
  "articles": [
    {
      "id": 1,
      "title": "Từ ngày mai, điện thoại \"bẻ khóa\" không thể mở ứng dụng ngân hàng",
      "summary": "<a href=\"https://dantri.com.vn/kinh-doanh/tu-ngay-mai-dien-thoai-be-khoa-khong-the-mo-ung-dung-ngan-hang-20260228084942953.htm\"><img src=\"https://icdn.dantri.com.vn/2026/02/21/huong-dan-ke-khai-nop-thue-cho-ho-ca-nhan-kinh-doanh-1771651112751.jpg\" /></a>(Dân trí) - Theo quy định mới có hiệu lực từ ngày mai (1/3), các thiết bị điện thoại bị bẻ khóa sẽ bị ứng dụng ngân hàng tự động ngắt kết nối để đảm bảo an toàn bảo mật."
    },
    {
      "id": 2,
      "title": "Kịch bản giá dầu nếu Iran phong tỏa \"yết hầu\" Hormuz",
      "summary": "<a href=\"https://dantri.com.vn/kinh-doanh/kich-ban-gia-dau-neu-iran-phong-toa-yet-hau-hormuz-20260228174137107.htm\"><img src=\"https://icdn.dantri.com.vn/2026/02/28/image-cropped-1772275167336.jpg\" /></a>(Dân trí) - Xung đột Iran - Israel gia tăng, làm dấy lên lo ngại về việc phong tỏa eo biển Hormuz - tuyến vận chuyển năng lượng quan trọng bậc nhất thế giới. Điều này liệu có khiến thị trường năng lượng chao đảo?"
    },
    {
      "id": 3,
      "title": "Mỹ - Israel không kích Iran: Giá vàng sắp bùng nổ?",
      "summary": "<a href=\"https://dantri.com.vn/kinh-doanh/my-israel-khong-kich-iran-gia-vang-sap-bung-no-20260228180135934.htm\"><img src=\"https://icdn.dantri.com.vn/2025/08/05/gia-vang-manh-quan-14-crop-edited-1754330788969.jpg\" /></a>(Dân trí) - Căng thẳng địa chính trị leo thang tại Trung Đông vào cuối tuần đã kích hoạt dòng tiền trú ẩn an toàn, đẩy giá vàng thế giới chốt tuần ở mức đỉnh 5.281 USD/ounce."
    }
  ]
}