{
  "articles": [
    {
      "id": 1,
      "title": "Tuyển nữ Việt Nam 1-0 Myanmar (Hiệp 1): Vạn Sự lập công",
      "summary": "<a href=\"https://dantri.com.vn/the-thao/tuyen-nu-viet-nam-1-0-myanmar-hiep-1-van-su-lap-cong-20251211154715060.htm\"><img src=\"https://icdn.dantri.com.vn/2025/12/11/thanhnhajpg-1765444141326.jpg\" /></a>(Dân trí) - Tuyển nữ Việt Nam ép sân Myanmar trên sân Chonburi (Thái Lan) chiều 11/12 ở bảng B bóng đá nữ SEA Games 33. Ngay phút thứ 8, Ngân Thị Vạn Sự đã mở tỷ số."
    },
    {
      "id": 2,
      "title": "U22 Việt Nam 1-0 U22 Malaysia (hiệp 1): Hiểu Minh mở tỷ số",
      "summary": "<a href=\"https://dantri.com.vn/the-thao/u22-viet-nam-1-0-u22-malaysia-hiep-1-hieu-minh-mo-ty-so-20251211110804015.htm\"><img src=\"https://icdn.dantri.com.vn/2025/12/11/u22-vietnamjpg-1765444379875.jpg\" /></a>(Dân trí) - Phút 11, Đình Bắc tạt bóng từ bên trái hướng về phía cột dọc xa, Hiểu Minh đã tì đè tốt và đánh đánh đầu chéo góc khiến thủ thành U22 Malaysia chôn chân đứng nhìn bóng đi vào lưới."
    },
    {
      "id": 3,
      "title": "Việt Nam có 4 đại diện ở nhóm 5 tay vợt pickleball xuất sắc nhất châu Á",
      "summary": "<a href=\"https://dantri.com.vn/the-thao/viet-nam-co-4-dai-dien-o-nhom-5-tay-vot-pickleball-xuat-sac-nhat-chau-a-20251211130647202.htm\"><img src=\"https://icdn.dantri.com.vn/2025/12/11/hoang-nam-hangzhoujpg-1765432383341.jpg\" /></a>(Dân trí) - Pickleball Việt Nam đang tạo nên địa chấn tại châu Á khi có tới 4 đại diện góp mặt trong top 5 tay vợt xuất sắc nhất PPA Tour Asia, khẳng định sức mạnh ở đấu trường châu lục."
    }
  ]
}