{
  "articles": [
    {
      "id": 1,
      "title": "Báo Brazil nói điều đặc biệt về Xuân Son trước trận gặp Malaysia",
      "summary": "<a href=\"https://dantri.com.vn/the-thao/bao-brazil-noi-dieu-dac-biet-ve-xuan-son-truoc-tran-gap-malaysia-20260325184750025.htm\"><img src=\"https://icdn.dantri.com.vn/2026/03/25/bao-brazil-binh-luan-ve-xuan-son-truoc-tran-quyet-chien-voi-malaysia-1774439126011.jpg\" /></a>(Dân trí) - Tờ Assessoria de Imprensa (Brazil) đã khen ngợi tiền đạo Xuân Son trước thềm trận đấu với Malaysia ở vòng loại Asian Cup 2027."
    },
    {
      "id": 2,
      "title": "U23 Thái Lan hòa kịch tính U23 Trung Quốc, U23 Việt Nam còn nguyên cơ hội",
      "summary": "<a href=\"https://dantri.com.vn/the-thao/u23-thai-lan-hoa-kich-tinh-u23-trung-quoc-u23-viet-nam-con-nguyen-co-hoi-20260325205206689.htm\"><img src=\"https://icdn.dantri.com.vn/2026/03/25/u23-trung-quoc-cropped-1774446660371.jpg\" /></a>(Dân trí) - Trong lượt trận mở màn, U23 Thái Lan và U23 Trung Quốc đã hòa nhau với tỷ số 2-2. Điều đó có nghĩa rằng, cả 4 đội bóng ở giải CFA Team China 2026 đều chỉ 1 điểm."
    },
    {
      "id": 3,
      "title": "Tiền đạo Malaysia tuyên bố đá vì danh dự trước đội tuyển Việt Nam",
      "summary": "<a href=\"https://dantri.com.vn/the-thao/tien-dao-malaysia-tuyen-bo-da-vi-danh-du-truoc-doi-tuyen-viet-nam-20260325183349190.htm\"><img src=\"https://icdn.dantri.com.vn/2026/03/25/safawi3fam25-3-26-cropped-1774437992726.jpg\" /></a>(Dân trí) - Trước trận đấu với đội tuyển Vệt Nam, tiền đạo Safawi Rasid của Malaysia cho biết đội bóng có biệt danh Harimau Malaya vẫn còn mục tiêu, đó là thi đấu vì danh dự."
    }
  ]
}