{
  "articles": [
    {
      "id": 1,
      "title": "Zverev không cảm thấy áp lực sau khi vô địch Roland Garros 2026",
      "summary": "<a href=\"https://dantri.com.vn/the-thao/zverev-khong-cam-thay-ap-luc-sau-khi-vo-dich-roland-garros-2026-20260617213437450.htm\"><img src=\"https://icdn.dantri.com.vn/2026/06/17/zverev-cropped-1781706766959.jpg\" /></a>(Dân trí) - Tay vợt Alexander Zverev chia sẻ anh không cảm thấy áp lực khi dự các giải đấu năm nay với vị thế của nhà đương kim vô địch Roland Garros."
    },
    {
      "id": 2,
      "title": "C.Ronaldo \"mất hút\", Bồ Đào Nha hòa thất vọng CHDC Congo",
      "summary": "<a href=\"https://dantri.com.vn/the-thao/cronaldo-mat-hut-bo-dao-nha-hoa-that-vong-chdc-congo-20260617223437736.htm\"><img src=\"https://icdn.dantri.com.vn/2026/06/18/bo-dao-nha-1-1-chdc-congo-het-hiep-1-c-cropped-1781721647143.jpg\" /></a>(Dân trí) - Cristiano Ronaldo \"mất hút' trên hàng công, khiến Bồ Đào Nha chịu trận hòa thất vọng với tỷ số 1-1 trước CHDC Congo."
    },
    {
      "id": 3,
      "title": "Nhận định Uzbekistan - Colombia (9h ngày 18/6): Bất ngờ lớn nổ ra",
      "summary": "<a href=\"https://dantri.com.vn/the-thao/nhan-dinh-uzbekistan-colombia-9h-ngay-186-bat-ngo-lon-no-ra-20260617173341310.htm\"><img src=\"https://icdn.dantri.com.vn/2026/06/17/6-bat-ngo-lon-no-ra-cropped-1781692325657.jpg\" /></a>(Dân trí) - Trận đấu giữa Uzbekistan và Colombia ở bảng K diễn ra vào lúc 9h ngày 18/6 trên sân Azteca (Mexico). Đại diện châu Á hoàn toàn có thể gây bất ngờ trong trận đấu này."
    }
  ]
}