{
  "articles": [
    {
      "id": 1,
      "title": "Nhật Bản lên tiếng về thông tin rời khỏi AFC",
      "summary": "<a href=\"https://dantri.com.vn/the-thao/nhat-ban-len-tieng-ve-thong-tin-roi-khoi-afc-20251103111024350.htm\"><img src=\"https://icdn.dantri.com.vn/2025/11/03/tuyen-nhat-ban-noi-thang-ve-kha-nang-roi-khoi-afc-cropped-1762142818947.jpg\" /></a>(Dân trí) - Chủ tịch Liên đoàn bóng đá Nhật Bản (JFA), Tsuneyasu Miyamoto, đã lên tiếng phủ nhận khả năng cơ quan này rời khỏi Liên đoàn bóng đá châu Á (AFC)."
    },
    {
      "id": 2,
      "title": "Mặt trái của việc vận động viên pickleball nam lạm dụng chơi “bao sân”",
      "summary": "<a href=\"https://dantri.com.vn/the-thao/mat-trai-cua-viec-van-dong-vien-pickleball-nam-lam-dung-choi-bao-san-20251103105132465.htm\"><img src=\"https://icdn.dantri.com.vn/2025/11/03/gettyimages-2218525035-612x612-cropped-1762141608023.jpg\" /></a>(Dân trí) - Trong pickleball, thi đấu đôi nam nữ đòi hỏi sự phối hợp chiến thuật tinh tế, nhưng một lỗi phổ biến và thường gây thua cuộc lại đến từ chính sự quá nhiệt tình của nam giới."
    },
    {
      "id": 3,
      "title": "HLV Hansi Flick tiết lộ tình hình chấn thương của Lamine Yamal",
      "summary": "<a href=\"https://dantri.com.vn/the-thao/hlv-hansi-flick-tiet-lo-tinh-hinh-chan-thuong-cua-lamine-yamal-20251103073508538.htm\"><img src=\"https://icdn.dantri.com.vn/2025/11/03/gettyimages-2244662580-612x612jpg-1762129789491.jpg\" /></a>(Dân trí) - HLV Hansi Flick cho rằng Lamine Yamal vẫn chưa thể trở lại đúng phong độ mặc dù anh vừa ghi bàn trong chiến thắng 3-1 của Barcelona trước Elche sáng 3/11 ở vòng 11 La Liga."
    }
  ]
}