{
  "articles": [
    {
      "id": 1,
      "title": "HLV Park Hang Seo có thể gia nhập CLB Thái Lan với mức lương cao",
      "summary": "<a href=\"https://dantri.com.vn/the-thao/hlv-park-hang-seo-co-the-gia-nhap-clb-thai-lan-voi-muc-luong-cao-20260512114551525.htm\"><img src=\"https://icdn.dantri.com.vn/2026/05/12/hlv-park-hang-seodocx-1658391204598-1690875040894-1697972555989-1778560966275.jpg\" /></a>(Dân trí) - Theo truyền thông Thái Lan, HLV Park Hang Seo nhận được lời mời từ CLB Kanchanaburi, đội bóng vừa xuống hạng ở giải vô địch quốc gia Thái Lan."
    },
    {
      "id": 2,
      "title": "Messi có tên trong danh sách sơ bộ tuyển Argentina dự World Cup 2026",
      "summary": "<a href=\"https://dantri.com.vn/the-thao/messi-co-ten-trong-danh-sach-so-bo-tuyen-argentina-du-world-cup-2026-20260512093255756.htm\"><img src=\"https://icdn.dantri.com.vn/2025/10/04/messi-cropped-1759538194989.jpg\" /></a>(Dân trí) - Liên đoàn bóng đá Argentina (AFA) đã chính thức công bố danh sách sơ bộ 55 cầu thủ tham dự World Cup 2026. Cái tên được mong chờ nhất Lionel Messi xuất hiện trong đội hình."
    },
    {
      "id": 3,
      "title": "HLV Cristiano Roland làm công tác tư tưởng với U17 Việt Nam",
      "summary": "<a href=\"https://dantri.com.vn/the-thao/hlv-cristiano-roland-lam-cong-tac-tu-tuong-voi-u17-viet-nam-20260512090556857.htm\"><img src=\"https://icdn.dantri.com.vn/2026/05/12/u17-viet-nam-cropped-1778551431882.jpg\" /></a>(Dân trí) - Bên cạnh sự chuẩn bị tốt nhất về đấu pháp, HLV Cristiano Roland cũng dành nhiều thời gian làm công tác tư tưởng với U17 Việt Nam, trước trận gặp U17 UAE vào 0h ngày 14/5."
    }
  ]
}