{
  "articles": [
    {
      "id": 1,
      "title": "Xác định 6 trận chung kết tranh vé dự World Cup 2026",
      "summary": "<a href=\"https://dantri.com.vn/the-thao/xac-dinh-6-tran-chung-ket-tranh-ve-du-world-cup-2026-20260327122207247.htm\"><img src=\"https://icdn.dantri.com.vn/2026/03/27/xac-dinh-6-tran-chung-ket-play-off-world-cup-2026-cropped-1774588896389.jpg\" /></a>(Dân trí) - Sau loạt trận đêm qua và sáng nay (27/3), FIFA đã xác định 6 trận chung kết play-off tham dự World Cup. 6 suất cuối giành vé tham dự giải đấu bóng đá số một hành tinh sẽ được xác định vào ngày 1/4."
    },
    {
      "id": 2,
      "title": "Đội tuyển Việt Nam nhận tin vui từ FIFA sau khi đánh bại Bangladesh",
      "summary": "<a href=\"https://dantri.com.vn/the-thao/doi-tuyen-viet-nam-nhan-tin-vui-tu-fifa-sau-khi-danh-bai-bangladesh-20260327110514427.htm\"><img src=\"https://icdn.dantri.com.vn/2026/03/26/bangladesh1manhquan-1774536453816.jpg\" /></a>(Dân trí) - Sau chiến thắng trước Bangladesh, tuyển Việt Nam đã được cộng 2,38 điểm trên bảng xếp hạng FIFA. Kết quả này giúp đoàn quân HLV Kim Sang Sik ngày càng thu hẹp khoảng cách với top 100."
    },
    {
      "id": 3,
      "title": "Khai mạc giải pickleball kỷ niệm Ngày truyền thống ngành Thể dục thể thao",
      "summary": "<a href=\"https://dantri.com.vn/the-thao/khai-mac-giai-pickleball-ky-niem-ngay-truyen-thong-nganh-the-duc-the-thao-20260327131102584.htm\"><img src=\"https://icdn.dantri.com.vn/2026/03/27/z7663204144437e2776c16ebcb322d31bd84c4ed55f71f-1774591465931.jpg\" /></a>(Dân trí) - Sáng 27/3, bầu không khí tại Khu liên hợp thể thao quốc gia Mỹ Đình trở nên sôi động với lễ khai mạc giải pickleball kỷ niệm 80 năm thành lập ngành Thể dục thể thao (TDTT) Việt Nam."
    }
  ]
}