{
  "articles": [
    {
      "id": 1,
      "title": "Dàn máy bay phun khói màu cờ Mỹ kỷ niệm 250 năm quốc khánh",
      "summary": "<a href=\"https://dantri.com.vn/the-gioi/dan-may-bay-phun-khoi-mau-co-my-ky-niem-250-nam-quoc-khanh-20260706114205972.htm\"><img src=\"https://icdn.dantri.com.vn/2026/07/06/trump-1-1781507434052-cropped-1783312831148.jpg\" /></a>(Dân trí) - Mỹ đã kỷ niệm 250 năm ngày lập quốc vào cuối tuần qua ở New York bằng một màn thể hiện hoành tráng của tàu và máy bay của nước này và các nước đối tác."
    },
    {
      "id": 2,
      "title": "Chiến sự Ukraine 6/7: Nga tập kích ồ ạt, Kiev hứng \"mua hỏa lực\"",
      "summary": "<a href=\"https://dantri.com.vn/the-gioi/chien-su-ukraine-67-nga-tap-kich-o-at-kiev-hung-mua-hoa-luc-20260706114950334.htm\"><img src=\"https://icdn.dantri.com.vn/2024/06/01/mig-31-kinzhal-nga-ukrainekqnga-crop-1717214582676.jpeg\" /></a>(Dân trí) - Trong đêm 5, rạng sáng 6/7, Nga tiến hành cuộc tập kích đường không quy mô lớn vào Ukraine với sự tham gia của máy bay ném bom chiến lược, tên lửa đạn đạo và tên lửa hành trình cùng hàng trăm UAV."
    },
    {
      "id": 3,
      "title": "Tài liệu mật của quân đội Anh được tìm thấy trong bãi rác",
      "summary": "<a href=\"https://dantri.com.vn/the-gioi/tai-lieu-mat-cua-quan-doi-anh-duoc-tim-thay-trong-bai-rac-20260706105543167.htm\"><img src=\"https://icdn.dantri.com.vn/2026/07/06/doanh-trai-anh-cropped-1783310069442.jpg\" /></a>(Dân trí) - Các tài liệu mật của quân đội Anh liên quan đến danh tính binh sĩ, nơi cất giữ vũ khí và các quy trình an ninh đã được tìm thấy trong bãi rác."
    }
  ]
}