{
  "articles": [
    {
      "id": 1,
      "title": "Cách Nga thay đổi toàn bộ ngành công nghiệp UAV",
      "summary": "<a href=\"https://dantri.com.vn/the-gioi/cach-nga-thay-doi-toan-bo-nganh-cong-nghiep-uav-20260713111233435.htm\"><img src=\"https://icdn.dantri.com.vn/2026/07/13/uav-ngasputnik-cropped-1783915692635.jpg\" /></a>(Dân trí) - Sau khi xung đột Nga - Ukraine bùng nổ, máy bay không người lái (UAV) nhanh chóng trở thành một trong những yếu tố quyết định cục diện chiến trường."
    },
    {
      "id": 2,
      "title": "Cựu Tổng thống Hàn Quốc Yoon Suk-yeol bị kết án 2 năm tù",
      "summary": "<a href=\"https://dantri.com.vn/the-gioi/cuu-tong-thong-han-quoc-yoon-suk-yeol-bi-ket-an-2-nam-tu-20260713154110742.htm\"><img src=\"https://icdn.dantri.com.vn/2026/07/13/unnamed-5-1783931588236.jpg\" /></a>(Dân trí) - Một tòa án Hàn Quốc tuyên án cựu Tổng thống Yoon Suk-yeol 2 năm tù trong phán quyết sơ thẩm xét xử ông về tội nhận dịch vụ thăm dò dư luận miễn phí."
    },
    {
      "id": 3,
      "title": "Ukraine dồn dập tấn công lãnh thổ Nga, Tổng thống Putin cảnh báo nóng",
      "summary": "<a href=\"https://dantri.com.vn/the-gioi/ukraine-don-dap-tan-cong-lanh-tho-nga-tong-thong-putin-canh-bao-nong-20260713222333698.htm\"><img src=\"https://icdn.dantri.com.vn/2026/05/10/putinreuters-cropped-1778366953981.jpg\" /></a>(Dân trí) - Tổng thống Vladimir Putin cảnh báo đòn đáp trả đối với những cuộc tấn công nhằm vào lãnh thổ Nga."
    }
  ]
}