{
  "articles": [
    {
      "id": 1,
      "title": "Cầu thủ nhập tịch Malaysia bị đội bóng Colombia cắt hợp đồng",
      "summary": "<a href=\"https://dantri.com.vn/the-thao/cau-thu-nhap-tich-malaysia-bi-doi-bong-colombia-cat-hop-dong-20251112225429733.htm\"><img src=\"https://icdn.dantri.com.vn/2025/11/12/holgado2nst12-11-25-cropped-1762962505498.jpg\" /></a>(Dân trí) - Tiền đạo Rodrigo Holgado của Malaysia bị CLB America de Cali (Colombia) thanh lý hợp đồng. Sự việc xảy ra không lâu sau khi Rodrigo Holgado cùng 6 cầu thủ nhập tịch khác của Malaysia bị FIFA treo giò."
    },
    {
      "id": 2,
      "title": "Phản ứng của CĐV Trung Quốc khi đội nhà gục ngã trước U22 Việt Nam",
      "summary": "<a href=\"https://dantri.com.vn/the-thao/phan-ung-cua-cdv-trung-quoc-khi-doi-nha-guc-nga-truoc-u22-viet-nam-20251112215709983.htm\"><img src=\"https://icdn.dantri.com.vn/2025/11/12/u22-trung-quocjpeg-1762959624895.jpeg\" /></a>(Dân trí) - Nhiều cổ động viên (CĐV) Trung Quốc đã bày tỏ sự thất vọng khi chứng kiến đội nhà gục ngã với tỷ số 0-1 trước U22 Việt Nam trong trận mở màn giải giao hữu Panda Cup."
    },
    {
      "id": 3,
      "title": "Cục diện giải tứ hùng sau khi U22 Việt Nam đánh bại U22 Trung Quốc",
      "summary": "<a href=\"https://dantri.com.vn/the-thao/cuc-dien-giai-tu-hung-sau-khi-u22-viet-nam-danh-bai-u22-trung-quoc-20251112214028664.htm\"><img src=\"https://icdn.dantri.com.vn/2025/11/12/u22vn3jpg-1762958259170.jpg\" /></a>(Dân trí) - Dù đánh bại chủ nhà U22 Trung Quốc 1-0 tối 12/11 nhưng U22 Việt Nam tạm xếp thứ hai ở giải tứ hùng CFA Team China - Panda Cup 2025 tại Thành Đô ."
    }
  ]
}