{
  "articles": [
    {
      "id": 1,
      "title": "Ukraine dùng 3 tiêm kích F-16 và Patriot để \"giăng bẫy\" bắn hạ Su-35 Nga?",
      "summary": "<a href=\"https://dantri.com.vn/the-gioi/ukraine-dung-3-tiem-kich-f-16-va-patriot-de-giang-bay-ban-ha-su-35-nga-20260710012006221.htm\"><img src=\"https://icdn.dantri.com.vn/2026/07/10/f-16-ukraineep-cropped-1783621047576.jpg\" /></a>(Dân trí) - Sau khi Ukraine tuyên bố hạ được máy bay chiến đấu Su-35 của Nga, xuất hiện những thông tin về cách Kiev có thể đã \"đặt bẫy\" đối phương."
    },
    {
      "id": 2,
      "title": "Nga đáp trả tối hậu thư của phương Tây, cảnh báo cứng rắn NATO",
      "summary": "<a href=\"https://dantri.com.vn/the-gioi/nga-dap-tra-toi-hau-thu-cua-phuong-tay-canh-bao-cung-ran-nato-20260710080416569.htm\"><img src=\"https://icdn.dantri.com.vn/2026/07/10/ngoai-truong-nga-lavrovtass-cropped-1783645299782.jpg\" /></a>(Dân trí) - Điện Kremlin cảnh báo việc NATO coi Nga là một mối đe dọa, đồng thời đáp trả tối hậu thư của phương Tây."
    },
    {
      "id": 3,
      "title": "Iran phóng loạt tên lửa, tấn công trung tâm chỉ huy và căn cứ quân sự Mỹ",
      "summary": "<a href=\"https://dantri.com.vn/the-gioi/iran-phong-loat-ten-lua-tan-cong-trung-tam-chi-huy-va-can-cu-quan-su-my-20260710064816105.htm\"><img src=\"https://icdn.dantri.com.vn/2026/07/10/ten-lua-iran-cropped-1783640737730.jpg\" /></a>(Dân trí) - Iran tuyên bố phóng tên lửa đạn đạo tấn công trung tâm chỉ huy và căn cứ không quân của Mỹ tại Trung Đông."
    }
  ]
}