{
  "articles": [
    {
      "id": 1,
      "title": "Tổng thống Putin gặp quan chức an ninh cấp cao Iran",
      "summary": "<a href=\"https://dantri.com.vn/the-gioi/tong-thong-putin-gap-quan-chuc-an-ninh-cap-cao-iran-20260131104845063.htm\"><img src=\"https://icdn.dantri.com.vn/2026/01/31/iran-cropped-1769831120220.jpg\" /></a>(Dân trí) - Tổng thống Nga Vladimir Putin đã có cuộc gặp với quan chức an ninh cấp cao của Iran trong bối cảnh căng thẳng leo thang với Mỹ."
    },
    {
      "id": 2,
      "title": "Chính phủ Mỹ lại đóng cửa một phần",
      "summary": "<a href=\"https://dantri.com.vn/the-gioi/chinh-phu-my-lai-dong-cua-mot-phan-20260131110628069.htm\"><img src=\"https://icdn.dantri.com.vn/2026/01/31/djpg-1769832211541.jpg\" /></a>(Dân trí) - Thượng viện Mỹ đã thông qua dự luật về ngân sách liên bang nhưng Hạ viện đang nghỉ nên chính phủ Mỹ dự kiến sẽ đóng cửa một phần trong ít nhất vài ngày tới."
    },
    {
      "id": 3,
      "title": "Vì sao Đức từ chối cung cấp tên lửa Patriot mới cho Ukraine?",
      "summary": "<a href=\"https://dantri.com.vn/the-gioi/vi-sao-duc-tu-choi-cung-cap-ten-lua-patriot-moi-cho-ukraine-20260131103219120.htm\"><img src=\"https://icdn.dantri.com.vn/2026/01/31/patriot-cropped-1769830211347.jpg\" /></a>(Dân trí) - Bộ trưởng Quốc phòng Đức Boris Pistorius đã đưa ra tuyên bố gây chú ý trong cuộc họp báo với người đồng cấp Litva tại Berlin: Đức hiện không thể cung cấp thêm hệ thống phòng không Patriot cho Ukraine."
    }
  ]
}