{
  "articles": [
    {
      "id": 1,
      "title": "Hội nghị Ankara và bước ngoặt từ NATO 2.0 sang 3.0",
      "summary": "<a href=\"https://dantri.com.vn/the-gioi/hoi-nghi-ankara-va-buoc-ngoat-tu-nato-20-sang-30-20260709224541111.htm\"><img src=\"https://icdn.dantri.com.vn/2026/07/09/nato-ankarareuters-cropped-1783611502711.jpg\" /></a>(Dân trí) - Khái niệm “NATO 3.0” ngày càng được giới nghiên cứu sử dụng để mô tả giai đoạn phát triển mới của liên minh quân sự này."
    },
    {
      "id": 2,
      "title": "Hỏa hoạn thiêu cháy nhà máy giày tại Trung Quốc, ít nhất 28 người chết",
      "summary": "<a href=\"https://dantri.com.vn/the-gioi/hoa-hoan-thieu-chay-nha-may-giay-tai-trung-quoc-it-nhat-28-nguoi-chet-20260710013115622.htm\"><img src=\"https://icdn.dantri.com.vn/2026/07/10/2148b3a017a78e92f714948d1f212898bf532cb8dc91ded710cb6f7598a33958-1783621647692.webp\" /></a>(Dân trí) - Vụ cháy lớn xảy ra hôm 9/7 ở khu nhà xưởng của một công ty sản xuất giày dép tại tỉnh Phúc Kiến, Trung Quốc đã gây thiệt hại lớn về người và tài sản, làm ít nhất 28 người thiệt mạng."
    },
    {
      "id": 3,
      "title": "Ukraine sắp nhận viện trợ khẩn cấp tên lửa đánh chặn Patriot",
      "summary": "<a href=\"https://dantri.com.vn/the-gioi/ukraine-sap-nhan-vien-tro-khan-cap-ten-lua-danh-chan-patriot-20260710051702741.htm\"><img src=\"https://icdn.dantri.com.vn/2025/08/01/patriotreuters11zon-cropped-1754037019635.jpg\" /></a>(Dân trí) - Tổng thống Volodymyr Zelensky cho biết, Mỹ sẽ cung cấp cho Ukraine một gói tên lửa chống đạn đạo mới dành cho hệ thống phòng không Patriot trong những ngày tới."
    }
  ]
}