{
  "articles": [
    {
      "id": 1,
      "title": "Real Madrid có nguy cơ mất ngôi đầu bảng vào tay Barcelona",
      "summary": "<a href=\"https://dantri.com.vn/the-thao/real-madrid-co-nguy-co-mat-ngoi-dau-bang-vao-tay-barcelona-20260222064239300.htm\"><img src=\"https://icdn.dantri.com.vn/2026/02/22/vinicius-cropped-1771717274409.jpg\" /></a>(Dân trí) - Real Madrid bất ngờ thua sốc 1-2 trước Osasuna sáng 22/2 và đứng trước nguy cơ mất ngôi đầu bảng La Liga vào tay Barcelona."
    },
    {
      "id": 2,
      "title": "Man City áp sát Arsenal, cuộc đua vô địch thêm nóng",
      "summary": "<a href=\"https://dantri.com.vn/the-thao/man-city-ap-sat-arsenal-cuoc-dua-vo-dich-them-nong-20260222064135356.htm\"><img src=\"https://icdn.dantri.com.vn/2026/02/22/man-city-1-cropped-1771717082034.jpg\" /></a>(Dân trí) - Man City đánh bại Newcastle 2-1 nhờ cú đúp của O’Reilly, qua đó rút ngắn cách biệt với Arsenal xuống còn hai điểm và gây sức ép lớn trước derby Bắc London."
    },
    {
      "id": 3,
      "title": "Carlos Alcaraz dễ dàng vô địch Qatar Open 2026",
      "summary": "<a href=\"https://dantri.com.vn/the-thao/carlos-alcaraz-de-dang-vo-dich-qatar-open-2026-20260222062447330.htm\"><img src=\"https://icdn.dantri.com.vn/2026/02/22/alcaraz-cropped-1771716157008.jpg\" /></a>(Dân trí) - Đánh bại Athur Fils trong trận chung kết sáng 22/2, Carlos Alcaraz lên ngôi vô địch giải ATP 500 Qatar Open 2026."
    }
  ]
}