{
  "articles": [
    {
      "id": 1,
      "title": "Thụy Sĩ 0-0 Colombia (hết hiệp 1): Thế trận giằng co",
      "summary": "<a href=\"https://dantri.com.vn/the-thao/thuy-si-0-0-colombia-het-hiep-1-the-tran-giang-co-20260708025014129.htm\"><img src=\"https://icdn.dantri.com.vn/2026/07/08/thuy-si-0-0-colombia-hiep-1-the-tran-giang-co-cropped-1783457455218.jpg\" /></a>(Dân trí) - Thụy Sĩ và Colombia chơi thận trọng trong cuộc chiến giành vé vào tứ kết World Cup 2026. Sau 45 phút đầu tiên, hai đội vẫn chưa thể khai thông thế bế tắc."
    },
    {
      "id": 2,
      "title": "Messi tỏa sáng, Argentina ngược dòng kinh điển đánh bại Ai Cập",
      "summary": "<a href=\"https://dantri.com.vn/the-thao/messi-toa-sang-argentina-nguoc-dong-kinh-dien-danh-bai-ai-cap-20260707222221415.htm\"><img src=\"https://icdn.dantri.com.vn/2026/07/08/messi-cropped-1783448261637.jpg\" /></a>(Dân trí) - Bị dẫn 2 bàn đến cuối trận, Argentina ngược dòng thắng Ai Cập 3-2 trên sân Atlanta (Mỹ) ở vòng 1/8 World Cup 2026 sáng 8/7. Messi và đồng đội giành vé vào tứ kết sau 90 phút đầy cảm xúc."
    },
    {
      "id": 3,
      "title": "Nước mắt Ronaldo, Modric, Neymar: Hồi kết của một thế hệ vĩ đại",
      "summary": "<a href=\"https://dantri.com.vn/the-thao/nuoc-mat-ronaldo-modric-neymar-hoi-ket-cua-mot-the-he-vi-dai-20260707145647286.htm\"><img src=\"https://icdn.dantri.com.vn/2026/07/07/7c2fc6d2-7c9e-40cc-b084-93999e3b0546-cropped-1783410636362.jpg\" /></a>(Dân trí) - Chiếc đồng hồ của những huyền thoại như Ronaldo, Luka Modric, Neymar ở World Cup đã dừng lại. Giờ đây, hình ảnh về họ chỉ được gói ghém lại trong ký ức của nhiều người…"
    }
  ]
}