{
  "articles": [
    {
      "id": 1,
      "title": "Bản người Thái ở biên giới nô nức đi bầu cử",
      "summary": "<a href=\"https://dantri.com.vn/thoi-su/ban-nguoi-thai-o-bien-gioi-no-nuc-di-bau-cu-20260315082047325.htm\"><img src=\"https://icdn.dantri.com.vn/2026/03/15/ban-nguoi-thai-di-bau-cu-somnghe-an-cropped-1773537554080.jpg?watermark=true\" /></a>(Dân trí) - Tại xã biên giới Môn Sơn (Nghệ An), nơi có nhiều bản 100% người Thái sinh sống, từ sáng sớm, cử tri đã nô nức đến điểm bỏ phiếu, thực hiện quyền và nghĩa vụ công dân."
    },
    {
      "id": 2,
      "title": "Xe đầu kéo bốc cháy dữ dội, tài xế không kịp thoát ra ngoài",
      "summary": "<a href=\"https://dantri.com.vn/thoi-su/xe-dau-keo-boc-chay-du-doi-tai-xe-khong-kip-thoat-ra-ngoai-20260315082717753.htm\"><img src=\"https://icdn.dantri.com.vn/2026/03/15/4250589223710404301-edited-1773537784494.jpg\" /></a>(Dân trí) - Đang di chuyển trên quốc lộ 1 qua Hà Tĩnh, ô tô đầu kéo mất lái, lao xuống bên đường rồi bốc cháy. Tài xế mắc kẹt bên trong và tử vong."
    },
    {
      "id": 3,
      "title": "Cử tri trên cả nước hân hoan đi bầu cử",
      "summary": "<a href=\"https://dantri.com.vn/thoi-su/cu-tri-tren-ca-nuoc-han-hoan-di-bau-cu-20260314225812418.htm\"><img src=\"https://icdn.dantri.com.vn/2026/03/15/bau-cu-6-cropped-cropped-1773538734408.jpg\" /></a>(Dân trí) - Từ biên giới tới hải đảo xa xôi, từ nông thôn đến thành thị, không khí rộn ràng diễn ra khắp các địa điểm bầu cử đại biểu Quốc hội khoá XVI và đại biểu Hội đồng nhân dân các cấp nhiệm kỳ 2026-2031."
    }
  ]
}