{
  "articles": [
    {
      "id": 1,
      "title": "Tổng thống Trump: Tôi muốn thấy xung đột Nga-Ukraine kết thúc",
      "summary": "<a href=\"https://dantri.com.vn/dt360/tong-thong-trump-toi-muon-thay-xung-dot-nga-ukraine-ket-thuc-20260620115645382.htm\"><img src=\"https://icdn.dantri.com.vn/2026/06/20/dich-cropped-1781931300523.jpg\" /></a>(Dân trí) - Phát biểu ngày 19/6, Tổng thống Mỹ Donald Trump cho biết Washington đang thúc đẩy các nỗ lực nhằm chấm dứt xung đột Nga - Ukraine và bày tỏ tin tưởng có thể đạt được mục tiêu này."
    },
    {
      "id": 2,
      "title": "Chiêu lừa \"thải độc bằng nước tương\" khiến nạn nhân mất hơn 1,5 triệu USD",
      "summary": "<a href=\"https://dantri.com.vn/suc-khoe/chieu-lua-thai-doc-bang-nuoc-tuong-khien-nan-nhan-mat-hon-15-trieu-usd-20260619143638564.htm\"><img src=\"https://icdn.dantri.com.vn/2026/06/19/trung-quoc-chieu-lua-thai-doc-bang-nuoc-tuong-khien-nguoi-cao-tuoi-mat-hon-15-trieu-usd-cropped-1781854488980.jpg\" /></a>(Dân trí) - Chỉ bằng chiêu trò dùng nước tương tạo ảo giác về độc tố, một mạng lưới phòng khám rởm tại Bắc Kinh (Trung Quốc) đã bòn rút hàng triệu USD từ những người cao tuổi neo đơn."
    },
    {
      "id": 3,
      "title": "Chiến sự Ukraine 20/6: Rộ tin Kiev đã thất thủ ở Liman",
      "summary": "<a href=\"https://dantri.com.vn/the-gioi/chien-su-ukraine-206-ro-tin-kiev-da-that-thu-o-liman-20260620113241435.htm\"><img src=\"https://icdn.dantri.com.vn/2026/06/20/moscow-main1781770645910hpmain-1781924235725.jpg\" /></a>(Dân trí) - Thành phố Liman được cho là đã thất thủ, Ukraine đang cấp tốc rút lui về phía tây. Đồng thời, quân đội Nga chiếm được khoảng 90% diện tích Konstantinovka."
    }
  ]
}