{
  "articles": [
    {
      "id": 1,
      "title": "Cháy suốt 30 giờ trên boong tàu sân bay lớn nhất thế giới của Mỹ gần Iran",
      "summary": "<a href=\"https://dantri.com.vn/the-gioi/chay-suot-30-gio-tren-boong-tau-san-bay-lon-nhat-the-gioi-cua-my-gan-iran-20260317103630410.htm\"><img src=\"https://icdn.dantri.com.vn/2026/03/17/tau-san-bay-fordafp11zon-1773718424679.jpg\" /></a>(Dân trí) - Một vụ cháy tại khu vực giặt là trên tàu sân bay USS Gerald R. Ford vào tuần trước đã kéo dài hơn 30 giờ và khiến hàng chục quân nhân trên tàu hít phải khói."
    },
    {
      "id": 2,
      "title": "Nam thanh niên ngoài 30 đã có khớp gối như người 70 tuổi",
      "summary": "<a href=\"https://dantri.com.vn/suc-khoe/nam-thanh-nien-ngoai-30-da-co-khop-goi-nhu-nguoi-70-tuoi-20260317100001735.htm\"><img src=\"https://icdn.dantri.com.vn/2026/03/17/shutterstock24682788691-1773716253543.jpeg\" /></a>(Dân trí) - Dù mới ngoài 30 tuổi, một nam nhân viên văn phòng tại TPHCM đã được chẩn đoán thoái hóa khớp gối nghiêm trọng như người cao tuổi."
    },
    {
      "id": 3,
      "title": "Công an thông tin vụ bé trai 10 tuổi bị bố đánh chi chít vết thương",
      "summary": "<a href=\"https://dantri.com.vn/thoi-su/cong-an-thong-tin-vu-be-trai-10-tuoi-bi-bo-danh-chi-chit-vet-thuong-20260317102831149.htm\"><img src=\"https://icdn.dantri.com.vn/2026/02/09/z7516232697387cf5c02ac2a6b75eeaa91dd56fcbbe653-edited-1770605145918.jpg\" /></a>(Dân trí) - Tức giận trước việc con trai 10 tuổi thường xuyên bỏ học, đi chơi, còn đập vỡ điện thoại của bà ngoại, người bố đã đánh con trai gây thương tích."
    }
  ]
}