{
  "articles": [
    {
      "id": 1,
      "title": "Dịch Ebola diễn biến phức tạp, Bộ Y tế khuyến cáo người dân 3 việc cần làm",
      "summary": "<a href=\"https://dantri.com.vn/suc-khoe/dich-ebola-dien-bien-phuc-tap-bo-y-te-khuyen-cao-nguoi-dan-3-viec-can-lam-20260529181758679.htm\"><img src=\"https://icdn.dantri.com.vn/2026/05/29/adobestockebola-edited-1780053412376.jpg\" /></a>(Dân trí) - Bộ Y tế đánh giá nguy cơ bệnh Ebola xâm nhập vào nước ta ở mức thấp. Tuy nhiên, không loại trừ khả năng ghi nhận ca bệnh xâm nhập, nhất là trong bối cảnh giao lưu đi lại quốc tế tiếp tục gia tăng."
    },
    {
      "id": 2,
      "title": "BRAVO 10 ERP khẳng định vị thế với Top 10 Sao Khuê 2026",
      "summary": "<a href=\"https://dantri.com.vn/kinh-doanh/bravo-10-erp-khang-dinh-vi-the-voi-top-10-sao-khue-2026-20260529193346551.htm\"><img src=\"https://icdn.dantri.com.vn/2026/05/29/anh-1anh-mr-hai-nhan-giai-1780055060191.jpg\" /></a>(Dân trí) - Phần mềm BRAVO 10 ERP vừa được vinh danh Top 10 Giải thưởng Sao Khuê 2026, tiếp tục khẳng định vị thế của doanh nghiệp Việt trong lĩnh vực quản trị tổng thể doanh nghiệp."
    },
    {
      "id": 3,
      "title": "Thiếu hụt nguồn cung, châu Á đứng trước nguy cơ \"cạn dầu\"",
      "summary": "<a href=\"https://dantri.com.vn/kinh-doanh/thieu-hut-nguon-cung-chau-a-dung-truoc-nguy-co-can-dau-20260528190818578.htm\"><img src=\"https://icdn.dantri.com.vn/2026/03/11/quan-bai-hormuz-va-bong-ma-khung-hoang-dau-mo-nam-2026-edited-1773241723585.jpg\" /></a>(Dân trí) - Thị trường dầu mỏ châu Á đang tiến sát ngưỡng tối thiểu để vận hành, khi nguồn cung toàn cầu ngày càng thắt chặt và lượng dầu liên tục suy giảm."
    }
  ]
}