{
  "articles": [
    {
      "id": 1,
      "title": "Chất thải hạt nhân thực sự nguy hiểm tới đâu?",
      "summary": "<a href=\"https://dantri.com.vn/khoa-hoc/chat-thai-hat-nhan-thuc-su-nguy-hiem-toi-dau-20260203015858715.htm\"><img src=\"https://icdn.dantri.com.vn/2026/02/03/chat-thai-hat-nhan-1-cropped-1770058665352.jpg\" /></a>(Dân trí) - Năng lượng hạt nhân là một trong những chủ đề gây tranh cãi nhất khi nói đến các phương pháp sản xuất điện. Sự thật đằng sau đó là gì, và chất thải hạt nhân có thực sự là một vấn đề lớn?"
    },
    {
      "id": 2,
      "title": "Vợ nghèo bó chổi 10.000 đồng/cây, nuôi chồng suy thận, con trai mù loà",
      "summary": "<a href=\"https://dantri.com.vn/tam-long-nhan-ai/vo-ngheo-bo-choi-10000-dongcay-nuoi-chong-suy-than-con-trai-mu-loa-20260129163917614.htm\"><img src=\"https://icdn.dantri.com.vn/2026/01/29/nhan-ai2bao-ky-edited-1769673691256.jpg?watermark=true\" /></a>(Dân trí) - Tiền bó chổi thuê chỉ 10.000 đồng/cây, còn bò mỗi năm chỉ bán được một con giá hơn 10 triệu đồng, nhưng đó là khoản thu nhập để chị Sang xoay xở nuôi chồng bị tiểu đường, suy thận, con trai mù loà."
    },
    {
      "id": 3,
      "title": "Duyên Quỳnh trước ồn ào hát nhép: Đổi đời nhờ hit tỷ view, nghi vấn hẹn hò",
      "summary": "<a href=\"https://dantri.com.vn/giai-tri/duyen-quynh-truoc-on-ao-hat-nhep-doi-doi-nho-hit-ty-view-nghi-van-hen-ho-20260205104502729.htm\"><img src=\"https://icdn.dantri.com.vn/2026/02/05/duyen-quynh-8-cropped-1770277048628.jpg\" /></a>(Dân trí) - Sau sự lan tỏa mạnh mẽ của \"Viết tiếp câu chuyện hòa bình\", Duyên Quỳnh trở thành gương mặt được chú ý tại nhiều sân khấu lớn. Mới đây, cô lại vướng tranh cãi liên quan đến kỹ năng biểu diễn."
    }
  ]
}