{
  "articles": [
    {
      "id": 1,
      "title": "Mỹ đưa 12 chiến đấu cơ đến Israel, sẵn sàng cho nhiệm vụ ở Iran?",
      "summary": "<a href=\"https://dantri.com.vn/the-gioi/my-dua-12-chien-dau-co-den-israel-san-sang-cho-nhiem-vu-o-iran-20260226105642139.htm\"><img src=\"https://icdn.dantri.com.vn/2026/02/26/f-22-cropped-1772077974708.jpg\" /></a>(Dân trí) - Mỹ điều động chiến đấu cơ hiện đại nhất đến Israel, đánh dấu lần đầu tiên triển khai máy bay chiến đấu đến nước này, sẵn sàng cho nhiệm vụ khi hai đồng minh có thể chuẩn bị đối đầu với Iran."
    },
    {
      "id": 2,
      "title": "\"Thỏ ơi\" đạt 300 tỷ đồng, Trấn Thành bất ngờ kêu gọi ủng hộ phim khác",
      "summary": "<a href=\"https://dantri.com.vn/giai-tri/tho-oi-dat-300-ty-dong-tran-thanh-bat-ngo-keu-goi-ung-ho-phim-khac-20260226111335453.htm\"><img src=\"https://icdn.dantri.com.vn/2026/02/26/d9391fb906768828d167-cropped-1772078923746.jpg\" /></a>(Dân trí) - Khi \"Thỏ ơi\" đang thắng lớn ngoài phòng vé, Trấn Thành vẫn dành sự quan tâm đặc biệt cho phim mới do em gái Uyển Ân đóng chính."
    },
    {
      "id": 3,
      "title": "Vụ tàu tông văng xe tải ở Hà Nội: Tài xế cố vượt, mắc kẹt trên đường ray",
      "summary": "<a href=\"https://dantri.com.vn/thoi-su/vu-tau-tong-vang-xe-tai-o-ha-noi-tai-xe-co-vuot-mac-ket-tren-duong-ray-20260226105805964.htm\"><img src=\"https://icdn.dantri.com.vn/2026/02/26/csgt4gif-1772078037794.gif\" /></a>(Dân trí) - Nhà chức trách cho hay, lái xe tải đã không chấp hành hiệu lệnh  tại nút giao với đường sắt, dẫn đến xe bị mắc kẹt trên đường ray và xảy ra tai nạn."
    }
  ]
}