{
  "articles": [
    {
      "id": 1,
      "title": "Giá dầu vượt 103 USD khi hàng loạt cơ sở năng lượng Trung Đông bị tấn công",
      "summary": "<a href=\"https://dantri.com.vn/kinh-doanh/gia-dau-vuot-103-usd-khi-hang-loat-co-so-nang-luong-trung-dong-bi-tan-cong-20260318062145901.htm\"><img src=\"https://icdn.dantri.com.vn/2026/03/18/crude-oil-9-3-2026-cropped-1773789082812.jpg\" /></a>(Dân trí) - Hàng loạt cuộc tấn công bằng thiết bị bay không người lái vào các mỏ dầu tại Trung Đông đã đẩy giá dầu Brent vượt mốc 103 USD/thùng, làm dấy lên nỗi lo đứt gãy an ninh năng lượng toàn cầu."
    },
    {
      "id": 2,
      "title": "Sửa quy định dạy thêm, học thêm là đúng, nhưng chưa đủ!",
      "summary": "<a href=\"https://dantri.com.vn/tam-diem/sua-quy-dinh-day-them-hoc-them-la-dung-nhung-chua-du-20260318062100944.htm\"><img src=\"https://icdn.dantri.com.vn/2026/03/18/sua-quy-dinh-day-them-hoc-them-la-dung-nhung-chua-du-1773789373085.jpg\" /></a>(Dân trí) - Điều quan trọng khi sửa Thông tư 29 là phải kéo học chính khóa trở lại đúng vị trí trung tâm. Và một khi giáo dục còn nặng “vị thi cử”, dạy thêm vẫn còn đất sống."
    },
    {
      "id": 3,
      "title": "Xe mất trộm vi phạm giao thông, cần làm gì để tránh mất tiền oan?",
      "summary": "<a href=\"https://dantri.com.vn/ban-doc/xe-mat-trom-vi-pham-giao-thong-can-lam-gi-de-tranh-mat-tien-oan-20260317040306572.htm\"><img src=\"https://icdn.dantri.com.vn/2026/03/17/anh-man-hinh-2026-03-12-luc-11-cropped-1773694736627.jpg\" /></a>(Dân trí) - Theo luật sư, khi phát hiện mất xe, người dân cần báo công an nơi gần nhất để lập biên bản tiếp nhận. Đây là chứng cứ pháp lý quan trọng giúp chủ xe tránh rắc rối nếu phát sinh phạt nguội."
    }
  ]
}