{
  "articles": [
    {
      "id": 1,
      "title": "Nhà sáng lập Sơn Kim Group và những trải lòng về thời trẻ \"đam mê, vất vả\"",
      "summary": "<a href=\"https://dantri.com.vn/kinh-doanh/nha-sang-lap-son-kim-group-va-nhung-trai-long-ve-thoi-tre-dam-me-vat-va-20260307155159872.htm\"><img src=\"https://icdn.dantri.com.vn/2026/03/07/ba-nguyen-thi-son-5-edited-cropped-cropped-1772872937543.jpg\" /></a>(Dân trí) - Nổi tiếng với vai trò một nữ doanh nhân, nữ luật gia, một nhà quản lý... nhưng ít ai biết bà Nguyễn Thị Sơn đã bước vào con đường khởi nghiệp từ tuổi 18."
    },
    {
      "id": 2,
      "title": "Ý nghĩa thật sự của ngày 8/3",
      "summary": "<a href=\"https://dantri.com.vn/tam-diem/y-nghia-that-su-cua-ngay-83-20260307203646313.htm\"><img src=\"https://icdn.dantri.com.vn/2026/03/07/tang-hoa-8-cropped-1772890412238.jpg\" /></a>(Dân trí) - 8/3 có thể bắt đầu bằng hoa và lời chúc. Nhưng thay vì chỉ có phần lễ, đây cũng là dịp nhắc nhở chúng ta nhìn thẳng vào những rào cản giới còn tồn tại."
    },
    {
      "id": 3,
      "title": "Hà Nội đón không khí lạnh, nhiều nơi có mưa rào",
      "summary": "<a href=\"https://dantri.com.vn/thoi-su/ha-noi-don-khong-khi-lanh-nhieu-noi-co-mua-rao-20260307214449616.htm\"><img src=\"https://icdn.dantri.com.vn/2026/03/07/ha-noi-sap-don-khong-khi-lanh-troi-chuyen-ret-nhieu-noi-co-mua-ra-1772894458831.jpg\" /></a>(Dân trí) - Dự báo từ đêm 8 đến sáng 10/3, Hà Nội có mưa, mưa rào rải rác và có nơi có dông, trời chuyển rét. Nhiệt độ thấp nhất trong đợt không khí lạnh này phổ biến 16-18 độ C."
    }
  ]
}